{
  "total_coins": 96,
  "signal_count": 22,
  "scan_time": 630.2,
  "signals": [
    {
      "id": null,
      "coin": "TON",
      "direction": "short",
      "grade": "A",
      "current_price": 1.67,
      "entry_low": 1.6602,
      "entry_high": 1.6783,
      "stop_loss": 1.7191,
      "take_profit": 1.5718,
      "risk_reward_ratio": 2.0,
      "confidence": 95.0,
      "sources": [
        {
          "name": "bigorder_anomaly",
          "score": 61.108859545019,
          "direction": "short",
          "weight": 0.3398,
          "detail": "12h聚合(Binance+Bybit+Bitget), 买$60K/卖$114K, 净流入$-54K, 599笔大单"
        },
        {
          "name": "quantitative",
          "score": 2.0,
          "direction": "neutral",
          "weight": 0.3516,
          "detail": "综合评分-2, 强度无, 置信度48.0%"
        },
        {
          "name": "technical",
          "score": 10.0,
          "direction": "short",
          "weight": 0.3288,
          "detail": "短期EMA偏空, ADX=15震荡市, RSI=41偏弱, RSI底背离, MACD死叉+零轴下方, Supertrend多头"
        }
      ],
      "win_rate": null,
      "sample_count": null,
      "avg_profit_pct": null,
      "position_pct": 5.6,
      "invalidation_price": 1.7191,
      "expires_at": null,
      "math": {
        "hurst": 0.5,
        "hurst_interpretation": "数据不足(需≥100)",
        "entropy_predictability": 0.2588,
        "kelly_fraction": 0.125,
        "monte_carlo_bull_prob": 0.486,
        "monte_carlo_bear_prob": 0.514,
        "monte_carlo_var95": -45.76,
        "vol_regime": "normal",
        "vol_percentile": 48.7,
        "market_regime": "trending_up",
        "market_regime_confidence": 0.571,
        "math_score_adjustment": 10.0,
        "math_confidence": 0.458,
        "key_findings": [
          "VaR(95%)=-45.8%，尾部风险大",
          "市场状态=trending_up，与信号方向一致"
        ]
      },
      "strategy": {
        "strategy_version": 1,
        "regime": "trending_up",
        "adaptive_weights": {
          "bigorder_anomaly": 0.3196,
          "quantitative": 0.3516,
          "technical": 0.3288
        },
        "global_win_rate": 0.5,
        "evolution_count": 0
      },
      "status": "pending",
      "created_at": "2026-06-10 15:15:17",
      "updated_at": "",
      "settled_at": null,
      "settled_price": null,
      "pnl_pct": null
    },
    {
      "id": null,
      "coin": "SENT",
      "direction": "short",
      "grade": "A",
      "current_price": 0.02,
      "entry_low": 0.019617,
      "entry_high": 0.0201,
      "stop_loss": 0.021915,
      "take_profit": 0.01617,
      "risk_reward_ratio": 2.0,
      "confidence": 95.0,
      "sources": [
        {
          "name": "bigorder_anomaly",
          "score": 45.739920197817945,
          "direction": "short",
          "weight": 0.3398,
          "detail": "12h聚合(Binance+Bybit+Bitget), 买$17K/卖$23K, 净流入$-6K, 600笔大单"
        },
        {
          "name": "quantitative",
          "score": 24.75,
          "direction": "short",
          "weight": 0.3516,
          "detail": "综合评分-25, 强度弱, 置信度50.0%"
        },
        {
          "name": "technical",
          "score": 52.0,
          "direction": "short",
          "weight": 0.3288,
          "detail": "EMA空头排列(9<21<55), RSI=68超买区, MACD柱正值, MACD顶背离, BB上轨(113%), Supertrend空头, 量价齐升"
        }
      ],
      "win_rate": null,
      "sample_count": null,
      "avg_profit_pct": null,
      "position_pct": 5.6,
      "invalidation_price": 0.021915,
      "expires_at": null,
      "math": {
        "hurst": 0.5,
        "hurst_interpretation": "数据不足(需≥100)",
        "entropy_predictability": 0.427,
        "kelly_fraction": 0.125,
        "monte_carlo_bull_prob": 0.535,
        "monte_carlo_bear_prob": 0.465,
        "monte_carlo_var95": -35.56,
        "vol_regime": "normal",
        "vol_percentile": 74.4,
        "market_regime": "trending_up",
        "market_regime_confidence": 1.0,
        "math_score_adjustment": 10.0,
        "math_confidence": 0.569,
        "key_findings": [
          "VaR(95%)=-35.6%，尾部风险大",
          "市场状态=trending_up，与信号方向一致"
        ]
      },
      "strategy": {
        "strategy_version": 1,
        "regime": "trending_up",
        "adaptive_weights": {
          "bigorder_anomaly": 0.3196,
          "quantitative": 0.3516,
          "technical": 0.3288
        },
        "global_win_rate": 0.5,
        "evolution_count": 0
      },
      "status": "pending",
      "created_at": "2026-06-10 15:15:28",
      "updated_at": "",
      "settled_at": null,
      "settled_price": null,
      "pnl_pct": null
    },
    {
      "id": null,
      "coin": "STG",
      "direction": "long",
      "grade": "A",
      "current_price": 0.39,
      "entry_low": 0.38805,
      "entry_high": 0.397189,
      "stop_loss": 0.354055,
      "take_profit": 0.461891,
      "risk_reward_ratio": 2.0,
      "confidence": 95.0,
      "sources": [
        {
          "name": "bigorder_anomaly",
          "score": 74.6040028766252,
          "direction": "long",
          "weight": 0.3398,
          "detail": "12h聚合(Binance+Bitget), 买$11K/卖$4K, 净流入$7K, 400笔大单"
        },
        {
          "name": "quantitative",
          "score": 2.0,
          "direction": "neutral",
          "weight": 0.3516,
          "detail": "综合评分-2, 强度无, 置信度48.0%"
        },
        {
          "name": "technical",
          "score": 30.0,
          "direction": "long",
          "weight": 0.3288,
          "detail": "EMA多头排列(9>21>55), ADX=35趋势强+DI多头, RSI=65超买区, MACD金叉+零轴上方, Supertrend空头, 量价背离"
        }
      ],
      "win_rate": null,
      "sample_count": null,
      "avg_profit_pct": null,
      "position_pct": 5.6,
      "invalidation_price": 0.354055,
      "expires_at": null,
      "math": {
        "hurst": 0.5,
        "hurst_interpretation": "数据不足(需≥100)",
        "entropy_predictability": 0.5061,
        "kelly_fraction": 0.125,
        "monte_carlo_bull_prob": 0.578,
        "monte_carlo_bear_prob": 0.422,
        "monte_carlo_var95": -55.57,
        "vol_regime": "extreme",
        "vol_percentile": 100.0,
        "market_regime": "trending_up",
        "market_regime_confidence": 0.5,
        "math_score_adjustment": 0.0,
        "math_confidence": 0.481,
        "key_findings": [
          "可预测性51%，信号可靠性高",
          "VaR(95%)=-55.6%，尾部风险大",
          "波动率极端(P100)，建议降仓",
          "市场状态=trending_up，与信号方向一致"
        ]
      },
      "strategy": {
        "strategy_version": 1,
        "regime": "trending_up",
        "adaptive_weights": {
          "bigorder_anomaly": 0.3196,
          "quantitative": 0.3516,
          "technical": 0.3288
        },
        "global_win_rate": 0.5,
        "evolution_count": 0
      },
      "status": "pending",
      "created_at": "2026-06-10 15:16:03",
      "updated_at": "",
      "settled_at": null,
      "settled_price": null,
      "pnl_pct": null
    },
    {
      "id": null,
      "coin": "JTO",
      "direction": "long",
      "grade": "S",
      "current_price": 0.61,
      "entry_low": 0.60695,
      "entry_high": 0.616041,
      "stop_loss": 0.579793,
      "take_profit": 0.670415,
      "risk_reward_ratio": 2.0,
      "confidence": 95.0,
      "sources": [
        {
          "name": "bigorder_anomaly",
          "score": 55.233958199377206,
          "direction": "long",
          "weight": 0.3398,
          "detail": "12h聚合(Binance+Bybit+Bitget), 买$14K/卖$9K, 净流入$6K, 599笔大单"
        },
        {
          "name": "quantitative",
          "score": 19.0,
          "direction": "long",
          "weight": 0.3516,
          "detail": "综合评分19, 强度弱, 置信度50.0%"
        },
        {
          "name": "technical",
          "score": 47.0,
          "direction": "long",
          "weight": 0.3288,
          "detail": "EMA多头排列(9>21>55), ADX=38趋势强+DI多头, MACD柱负值, BB中部(60%), Supertrend多头, 量价齐升"
        }
      ],
      "win_rate": null,
      "sample_count": null,
      "avg_profit_pct": null,
      "position_pct": 9.0,
      "invalidation_price": 0.579793,
      "expires_at": null,
      "math": {
        "hurst": 0.5,
        "hurst_interpretation": "数据不足(需≥100)",
        "entropy_predictability": 0.2805,
        "kelly_fraction": 0.125,
        "monte_carlo_bull_prob": 0.673,
        "monte_carlo_bear_prob": 0.327,
        "monte_carlo_var95": -41.51,
        "vol_regime": "normal",
        "vol_percentile": 46.2,
        "market_regime": "trending_up",
        "market_regime_confidence": 1.0,
        "math_score_adjustment": 30.0,
        "math_confidence": 0.547,
        "key_findings": [
          "MC上涨概率67%，方向确认",
          "VaR(95%)=-41.5%，尾部风险大",
          "市场状态=trending_up，与信号方向一致"
        ]
      },
      "strategy": {
        "strategy_version": 1,
        "regime": "trending_up",
        "adaptive_weights": {
          "bigorder_anomaly": 0.3196,
          "quantitative": 0.3516,
          "technical": 0.3288
        },
        "global_win_rate": 0.5,
        "evolution_count": 0
      },
      "status": "pending",
      "created_at": "2026-06-10 15:17:33",
      "updated_at": "",
      "settled_at": null,
      "settled_price": null,
      "pnl_pct": null
    },
    {
      "id": null,
      "coin": "ONDO",
      "direction": "short",
      "grade": "A",
      "current_price": 0.35,
      "entry_low": 0.347462,
      "entry_high": 0.35175,
      "stop_loss": 0.362691,
      "take_profit": 0.328848,
      "risk_reward_ratio": 1.7,
      "confidence": 93.5,
      "sources": [
        {
          "name": "bigorder_anomaly",
          "score": 51.488832669862575,
          "direction": "short",
          "weight": 0.3398,
          "detail": "12h聚合(Binance+Bybit+Bitget), 买$46K/卖$71K, 净流入$-25K, 600笔大单"
        },
        {
          "name": "quantitative",
          "score": 18.0,
          "direction": "short",
          "weight": 0.3516,
          "detail": "综合评分-18, 强度弱, 置信度50.0%"
        },
        {
          "name": "technical",
          "score": 35.0,
          "direction": "short",
          "weight": 0.3288,
          "detail": "短期EMA偏空, RSI=43偏弱, MACD死叉+零轴下方, BB下轨(9%), Supertrend空头"
        }
      ],
      "win_rate": null,
      "sample_count": null,
      "avg_profit_pct": null,
      "position_pct": 5.6,
      "invalidation_price": 0.362691,
      "expires_at": null,
      "math": {
        "hurst": 0.5,
        "hurst_interpretation": "数据不足(需≥100)",
        "entropy_predictability": 0.2187,
        "kelly_fraction": 0.125,
        "monte_carlo_bull_prob": 0.612,
        "monte_carlo_bear_prob": 0.388,
        "monte_carlo_var95": -33.93,
        "vol_regime": "normal",
        "vol_percentile": 51.3,
        "market_regime": "trending_down",
        "market_regime_confidence": 1.0,
        "math_score_adjustment": -5.0,
        "math_confidence": 0.538,
        "key_findings": [
          "可预测性22%过低，噪音主导",
          "MC上涨概率61%，方向确认",
          "VaR(95%)=-33.9%，尾部风险大"
        ]
      },
      "strategy": {
        "strategy_version": 1,
        "regime": "trending_down",
        "adaptive_weights": {
          "bigorder_anomaly": 0.3196,
          "quantitative": 0.3516,
          "technical": 0.3288
        },
        "global_win_rate": 0.5,
        "evolution_count": 0
      },
      "status": "pending",
      "created_at": "2026-06-10 15:15:36",
      "updated_at": "",
      "settled_at": null,
      "settled_price": null,
      "pnl_pct": null
    },
    {
      "id": null,
      "coin": "TIA",
      "direction": "short",
      "grade": "A",
      "current_price": 0.32,
      "entry_low": 0.318051,
      "entry_high": 0.3216,
      "stop_loss": 0.329746,
      "take_profit": 0.300509,
      "risk_reward_ratio": 2.0,
      "confidence": 93.5,
      "sources": [
        {
          "name": "bigorder_anomaly",
          "score": 51.140444607064765,
          "direction": "short",
          "weight": 0.3398,
          "detail": "12h聚合(Binance+Bybit+Bitget), 买$11K/卖$17K, 净流入$-6K, 600笔大单"
        },
        {
          "name": "quantitative",
          "score": 12.0,
          "direction": "short",
          "weight": 0.3516,
          "detail": "综合评分-12, 强度弱, 置信度50.0%"
        },
        {
          "name": "technical",
          "score": 35.0,
          "direction": "short",
          "weight": 0.3288,
          "detail": "EMA空头排列(9<21<55), ADX=29趋势强+DI空头, RSI=34超卖区, MACD死叉+零轴下方, Supertrend多头"
        }
      ],
      "win_rate": null,
      "sample_count": null,
      "avg_profit_pct": null,
      "position_pct": 5.6,
      "invalidation_price": 0.329746,
      "expires_at": null,
      "math": {
        "hurst": 0.5,
        "hurst_interpretation": "数据不足(需≥100)",
        "entropy_predictability": 0.2402,
        "kelly_fraction": 0.125,
        "monte_carlo_bull_prob": 0.474,
        "monte_carlo_bear_prob": 0.526,
        "monte_carlo_var95": -38.31,
        "vol_regime": "normal",
        "vol_percentile": 53.8,
        "market_regime": "trending_up",
        "market_regime_confidence": 0.571,
        "math_score_adjustment": -5.0,
        "math_confidence": 0.455,
        "key_findings": [
          "可预测性24%过低，噪音主导",
          "VaR(95%)=-38.3%，尾部风险大",
          "市场状态=trending_up，与信号方向一致"
        ]
      },
      "strategy": {
        "strategy_version": 1,
        "regime": "trending_up",
        "adaptive_weights": {
          "bigorder_anomaly": 0.3196,
          "quantitative": 0.3516,
          "technical": 0.3288
        },
        "global_win_rate": 0.5,
        "evolution_count": 0
      },
      "status": "pending",
      "created_at": "2026-06-10 15:20:58",
      "updated_at": "",
      "settled_at": null,
      "settled_price": null,
      "pnl_pct": null
    },
    {
      "id": null,
      "coin": "IO",
      "direction": "long",
      "grade": "A",
      "current_price": 0.17,
      "entry_low": 0.16915,
      "entry_high": 0.172184,
      "stop_loss": 0.155438,
      "take_profit": 0.184562,
      "risk_reward_ratio": 1.0,
      "confidence": 92.0,
      "sources": [
        {
          "name": "bigorder_anomaly",
          "score": 45.509559855056104,
          "direction": "long",
          "weight": 0.3398,
          "detail": "12h聚合(Binance+Bybit+Bitget), 买$55K/卖$40K, 净流入$15K, 600笔大单"
        },
        {
          "name": "quantitative",
          "score": 6.0,
          "direction": "neutral",
          "weight": 0.3377,
          "detail": "综合评分-6, 强度无, 置信度48.0%"
        },
        {
          "name": "technical",
          "score": 12.0,
          "direction": "long",
          "weight": 0.2632,
          "detail": "短期EMA偏空, ADX=33趋势强+DI多头, MACD柱负值, BB中部(45%), Supertrend多头, 量价齐升"
        }
      ],
      "win_rate": null,
      "sample_count": null,
      "avg_profit_pct": null,
      "position_pct": 5.6,
      "invalidation_price": 0.155438,
      "expires_at": null,
      "math": {
        "hurst": 0.5,
        "hurst_interpretation": "数据不足(需≥100)",
        "entropy_predictability": 0.487,
        "kelly_fraction": 0.125,
        "monte_carlo_bull_prob": 0.546,
        "monte_carlo_bear_prob": 0.454,
        "monte_carlo_var95": -56.17,
        "vol_regime": "normal",
        "vol_percentile": 48.7,
        "market_regime": "mean_reverting",
        "market_regime_confidence": 0.571,
        "math_score_adjustment": -10.0,
        "math_confidence": 0.492,
        "key_findings": [
          "VaR(95%)=-56.2%，尾部风险大"
        ]
      },
      "strategy": {
        "strategy_version": 1,
        "regime": "mean_reverting",
        "adaptive_weights": {
          "bigorder_anomaly": 0.3991,
          "quantitative": 0.3377,
          "technical": 0.2632
        },
        "global_win_rate": 0.5,
        "evolution_count": 0
      },
      "status": "pending",
      "created_at": "2026-06-10 15:16:42",
      "updated_at": "",
      "settled_at": null,
      "settled_price": null,
      "pnl_pct": null
    },
    {
      "id": null,
      "coin": "BIO",
      "direction": "short",
      "grade": "A",
      "current_price": 0.03,
      "entry_low": 0.029752,
      "entry_high": 0.03015,
      "stop_loss": 0.031238,
      "take_profit": 0.027937,
      "risk_reward_ratio": 1.7,
      "confidence": 92.0,
      "sources": [
        {
          "name": "bigorder_anomaly",
          "score": 51.66301051819285,
          "direction": "short",
          "weight": 0.3398,
          "detail": "12h聚合(Binance+Bitget), 买$13K/卖$21K, 净流入$-7K, 399笔大单"
        },
        {
          "name": "quantitative",
          "score": 32.75,
          "direction": "short",
          "weight": 0.3516,
          "detail": "综合评分-33, 强度中等, 置信度57.0%"
        },
        {
          "name": "technical",
          "score": 45.0,
          "direction": "short",
          "weight": 0.3288,
          "detail": "EMA空头排列(9<21<55), ADX=16震荡市, RSI=43偏弱, MACD死叉+零轴下方, Supertrend多头, 量价背离"
        }
      ],
      "win_rate": null,
      "sample_count": null,
      "avg_profit_pct": null,
      "position_pct": 5.6,
      "invalidation_price": 0.031238,
      "expires_at": null,
      "math": {
        "hurst": 0.5,
        "hurst_interpretation": "数据不足(需≥100)",
        "entropy_predictability": 0.252,
        "kelly_fraction": 0.125,
        "monte_carlo_bull_prob": 0.504,
        "monte_carlo_bear_prob": 0.496,
        "monte_carlo_var95": -65.42,
        "vol_regime": "normal",
        "vol_percentile": 46.2,
        "market_regime": "trending_down",
        "market_regime_confidence": 1.0,
        "math_score_adjustment": -10.0,
        "math_confidence": 0.543,
        "key_findings": [
          "VaR(95%)=-65.4%，尾部风险大"
        ]
      },
      "strategy": {
        "strategy_version": 1,
        "regime": "trending_down",
        "adaptive_weights": {
          "bigorder_anomaly": 0.3196,
          "quantitative": 0.3516,
          "technical": 0.3288
        },
        "global_win_rate": 0.5,
        "evolution_count": 0
      },
      "status": "pending",
      "created_at": "2026-06-10 15:18:18",
      "updated_at": "",
      "settled_at": null,
      "settled_price": null,
      "pnl_pct": null
    },
    {
      "id": null,
      "coin": "SAHARA",
      "direction": "short",
      "grade": "A",
      "current_price": 0.02,
      "entry_low": 0.01959,
      "entry_high": 0.0201,
      "stop_loss": 0.02164,
      "take_profit": 0.015215,
      "risk_reward_ratio": 2.9,
      "confidence": 87.5,
      "sources": [
        {
          "name": "bigorder_anomaly",
          "score": 51.12776975759075,
          "direction": "short",
          "weight": 0.3398,
          "detail": "12h聚合(Binance+Bybit+Bitget), 买$14K/卖$22K, 净流入$-8K, 598笔大单"
        },
        {
          "name": "quantitative",
          "score": 2.0,
          "direction": "neutral",
          "weight": 0.3398,
          "detail": "综合评分-2, 强度无, 置信度48.0%"
        },
        {
          "name": "technical",
          "score": 10.0,
          "direction": "short",
          "weight": 0.3204,
          "detail": "短期EMA偏空, ADX=34趋势强+DI空头, RSI=32超卖区, MACD死叉+零轴下方, BB下轨(-46%), Supertrend多头"
        }
      ],
      "win_rate": null,
      "sample_count": null,
      "avg_profit_pct": null,
      "position_pct": 5.6,
      "invalidation_price": 0.02164,
      "expires_at": null,
      "math": {
        "hurst": 0.5,
        "hurst_interpretation": "数据不足(需≥100)",
        "entropy_predictability": 0.4616,
        "kelly_fraction": 0.125,
        "monte_carlo_bull_prob": 0.37,
        "monte_carlo_bear_prob": 0.63,
        "monte_carlo_var95": -68.72,
        "vol_regime": "low",
        "vol_percentile": 17.9,
        "market_regime": "quiet",
        "market_regime_confidence": 0.625,
        "math_score_adjustment": -25.0,
        "math_confidence": 0.499,
        "key_findings": [
          "MC上涨概率仅37%，方向存疑",
          "VaR(95%)=-68.7%，尾部风险大",
          "波动率低位(P18)，趋势可靠"
        ]
      },
      "strategy": {
        "strategy_version": 1,
        "regime": "quiet",
        "adaptive_weights": {
          "bigorder_anomaly": 0.3398,
          "quantitative": 0.3398,
          "technical": 0.3204
        },
        "global_win_rate": 0.5,
        "evolution_count": 0
      },
      "status": "pending",
      "created_at": "2026-06-10 15:13:50",
      "updated_at": "",
      "settled_at": null,
      "settled_price": null,
      "pnl_pct": null
    },
    {
      "id": null,
      "coin": "WLFI",
      "direction": "short",
      "grade": "A",
      "current_price": 0.06,
      "entry_low": 0.059706,
      "entry_high": 0.060294,
      "stop_loss": 0.061468,
      "take_profit": 0.057554,
      "risk_reward_ratio": 1.7,
      "confidence": 87.5,
      "sources": [
        {
          "name": "bigorder_anomaly",
          "score": 57.23277884704414,
          "direction": "short",
          "weight": 0.3398,
          "detail": "12h聚合(Binance+Bybit+Bitget), 买$57K/卖$99K, 净流入$-43K, 581笔大单"
        },
        {
          "name": "quantitative",
          "score": 19.25,
          "direction": "short",
          "weight": 0.3516,
          "detail": "综合评分-19, 强度弱, 置信度50.0%"
        },
        {
          "name": "technical",
          "score": 17.0,
          "direction": "short",
          "weight": 0.3288,
          "detail": "EMA空头排列(9<21<55), ADX=18震荡市, RSI=44偏弱, MACD柱正值, Supertrend多头"
        }
      ],
      "win_rate": null,
      "sample_count": null,
      "avg_profit_pct": null,
      "position_pct": 5.6,
      "invalidation_price": 0.061468,
      "expires_at": null,
      "math": {
        "hurst": 0.5,
        "hurst_interpretation": "数据不足(需≥100)",
        "entropy_predictability": 0.2881,
        "kelly_fraction": 0.125,
        "monte_carlo_bull_prob": 0.234,
        "monte_carlo_bear_prob": 0.766,
        "monte_carlo_var95": -36.38,
        "vol_regime": "low",
        "vol_percentile": 7.7,
        "market_regime": "trending_down",
        "market_regime_confidence": 0.583,
        "math_score_adjustment": -25.0,
        "math_confidence": 0.465,
        "key_findings": [
          "MC上涨概率仅23%，方向存疑",
          "VaR(95%)=-36.4%，尾部风险大",
          "波动率低位(P8)，趋势可靠"
        ]
      },
      "strategy": {
        "strategy_version": 1,
        "regime": "trending_down",
        "adaptive_weights": {
          "bigorder_anomaly": 0.3196,
          "quantitative": 0.3516,
          "technical": 0.3288
        },
        "global_win_rate": 0.5,
        "evolution_count": 0
      },
      "status": "pending",
      "created_at": "2026-06-10 15:20:30",
      "updated_at": "",
      "settled_at": null,
      "settled_price": null,
      "pnl_pct": null
    },
    {
      "id": null,
      "coin": "WAL",
      "direction": "short",
      "grade": "A",
      "current_price": 0.03,
      "entry_low": 0.029562,
      "entry_high": 0.03015,
      "stop_loss": 0.032919,
      "take_profit": 0.027081,
      "risk_reward_ratio": 1.0,
      "confidence": 87.5,
      "sources": [
        {
          "name": "bigorder_anomaly",
          "score": 15.133165571236418,
          "direction": "neutral",
          "weight": 0.3398,
          "detail": "12h聚合(Binance+Bybit+Bitget), 买$42K/卖$42K, 净流入$-222, 600笔大单"
        },
        {
          "name": "quantitative",
          "score": 19.0,
          "direction": "short",
          "weight": 0.3377,
          "detail": "综合评分-19, 强度弱, 置信度50.0%"
        },
        {
          "name": "technical",
          "score": 35.0,
          "direction": "short",
          "weight": 0.2632,
          "detail": "EMA空头排列(9<21<55), ADX=47趋势强+DI空头, RSI=19严重超卖, MACD死叉+零轴下方, BB下轨(0%), Supertrend空头"
        }
      ],
      "win_rate": null,
      "sample_count": null,
      "avg_profit_pct": null,
      "position_pct": 5.6,
      "invalidation_price": 0.032919,
      "expires_at": null,
      "math": {
        "hurst": 0.5,
        "hurst_interpretation": "数据不足(需≥100)",
        "entropy_predictability": 0.5719,
        "kelly_fraction": 0.125,
        "monte_carlo_bull_prob": 0.163,
        "monte_carlo_bear_prob": 0.837,
        "monte_carlo_var95": -74.6,
        "vol_regime": "normal",
        "vol_percentile": 59.0,
        "market_regime": "mean_reverting",
        "market_regime_confidence": 0.571,
        "math_score_adjustment": -25.0,
        "math_confidence": 0.505,
        "key_findings": [
          "可预测性57%，信号可靠性高",
          "MC上涨概率仅16%，方向存疑",
          "VaR(95%)=-74.6%，尾部风险大"
        ]
      },
      "strategy": {
        "strategy_version": 1,
        "regime": "mean_reverting",
        "adaptive_weights": {
          "bigorder_anomaly": 0.3991,
          "quantitative": 0.3377,
          "technical": 0.2632
        },
        "global_win_rate": 0.5,
        "evolution_count": 0
      },
      "status": "pending",
      "created_at": "2026-06-10 15:21:14",
      "updated_at": "",
      "settled_at": null,
      "settled_price": null,
      "pnl_pct": null
    },
    {
      "id": null,
      "coin": "SUI",
      "direction": "short",
      "grade": "A",
      "current_price": 0.75,
      "entry_low": 0.746515,
      "entry_high": 0.753485,
      "stop_loss": 0.767425,
      "take_profit": 0.720959,
      "risk_reward_ratio": 1.7,
      "confidence": 84.5,
      "sources": [
        {
          "name": "bigorder_anomaly",
          "score": 42.409629842693114,
          "direction": "short",
          "weight": 0.3398,
          "detail": "12h聚合(Binance+Bybit+Bitget), 买$41K/卖$53K, 净流入$-12K, 600笔大单"
        },
        {
          "name": "quantitative",
          "score": 27.0,
          "direction": "short",
          "weight": 0.3516,
          "detail": "综合评分-27, 强度弱, 置信度50.0%"
        },
        {
          "name": "technical",
          "score": 55.0,
          "direction": "short",
          "weight": 0.3288,
          "detail": "EMA空头排列(9<21<55), ADX=29趋势强+DI空头, RSI=29超卖区, MACD死叉+零轴下方, Supertrend空头"
        }
      ],
      "win_rate": null,
      "sample_count": null,
      "avg_profit_pct": null,
      "position_pct": 5.6,
      "invalidation_price": 0.767425,
      "expires_at": null,
      "math": {
        "hurst": 0.5,
        "hurst_interpretation": "数据不足(需≥100)",
        "entropy_predictability": 0.4373,
        "kelly_fraction": 0.125,
        "monte_carlo_bull_prob": 0.295,
        "monte_carlo_bear_prob": 0.705,
        "monte_carlo_var95": -38.97,
        "vol_regime": "normal",
        "vol_percentile": 46.2,
        "market_regime": "trending_down",
        "market_regime_confidence": 1.0,
        "math_score_adjustment": -35.0,
        "math_confidence": 0.571,
        "key_findings": [
          "MC上涨概率仅30%，方向存疑",
          "VaR(95%)=-39.0%，尾部风险大"
        ]
      },
      "strategy": {
        "strategy_version": 1,
        "regime": "trending_down",
        "adaptive_weights": {
          "bigorder_anomaly": 0.3196,
          "quantitative": 0.3516,
          "technical": 0.3288
        },
        "global_win_rate": 0.5,
        "evolution_count": 0
      },
      "status": "pending",
      "created_at": "2026-06-10 15:14:04",
      "updated_at": "",
      "settled_at": null,
      "settled_price": null,
      "pnl_pct": null
    },
    {
      "id": null,
      "coin": "DASH",
      "direction": "short",
      "grade": "A",
      "current_price": 34.62,
      "entry_low": 34.3898,
      "entry_high": 34.7931,
      "stop_loss": 35.771,
      "take_profit": 32.7017,
      "risk_reward_ratio": 1.7,
      "confidence": 84.5,
      "sources": [
        {
          "name": "bigorder_anomaly",
          "score": 42.05854460931564,
          "direction": "short",
          "weight": 0.3398,
          "detail": "12h聚合(Binance), 买$17K/卖$22K, 净流入$-5K, 200笔大单"
        },
        {
          "name": "quantitative",
          "score": 16.75,
          "direction": "short",
          "weight": 0.3516,
          "detail": "综合评分-17, 强度弱, 置信度50.0%"
        },
        {
          "name": "technical",
          "score": 35.0,
          "direction": "short",
          "weight": 0.3288,
          "detail": "EMA空头排列(9<21<55), ADX=16震荡市, RSI=37偏弱, MACD死叉+零轴下方, Supertrend多头, 量价齐升"
        }
      ],
      "win_rate": null,
      "sample_count": null,
      "avg_profit_pct": null,
      "position_pct": 5.6,
      "invalidation_price": 35.771,
      "expires_at": null,
      "math": {
        "hurst": 0.5,
        "hurst_interpretation": "数据不足(需≥100)",
        "entropy_predictability": 0.3453,
        "kelly_fraction": 0.125,
        "monte_carlo_bull_prob": 0.29,
        "monte_carlo_bear_prob": 0.71,
        "monte_carlo_var95": -49.63,
        "vol_regime": "normal",
        "vol_percentile": 53.8,
        "market_regime": "trending_down",
        "market_regime_confidence": 1.0,
        "math_score_adjustment": -35.0,
        "math_confidence": 0.557,
        "key_findings": [
          "MC上涨概率仅29%，方向存疑",
          "VaR(95%)=-49.6%，尾部风险大"
        ]
      },
      "strategy": {
        "strategy_version": 1,
        "regime": "trending_down",
        "adaptive_weights": {
          "bigorder_anomaly": 0.3196,
          "quantitative": 0.3516,
          "technical": 0.3288
        },
        "global_win_rate": 0.5,
        "evolution_count": 0
      },
      "status": "pending",
      "created_at": "2026-06-10 15:16:52",
      "updated_at": "",
      "settled_at": null,
      "settled_price": null,
      "pnl_pct": null
    },
    {
      "id": null,
      "coin": "FIL",
      "direction": "short",
      "grade": "A",
      "current_price": 0.76,
      "entry_low": 0.756166,
      "entry_high": 0.7638,
      "stop_loss": 0.779172,
      "take_profit": 0.728047,
      "risk_reward_ratio": 1.7,
      "confidence": 84.5,
      "sources": [
        {
          "name": "bigorder_anomaly",
          "score": 55.09715185215187,
          "direction": "short",
          "weight": 0.3398,
          "detail": "12h聚合(Binance+Bybit+Bitget), 买$72K/卖$120K, 净流入$-48K, 600笔大单"
        },
        {
          "name": "quantitative",
          "score": 0.75,
          "direction": "neutral",
          "weight": 0.3516,
          "detail": "综合评分-1, 强度无, 置信度48.0%"
        },
        {
          "name": "technical",
          "score": 30.0,
          "direction": "short",
          "weight": 0.3288,
          "detail": "EMA空头排列(9<21<55), ADX=14震荡市, RSI=33超卖区, MACD死叉+零轴下方, BB下轨(2%), Supertrend空头"
        }
      ],
      "win_rate": null,
      "sample_count": null,
      "avg_profit_pct": null,
      "position_pct": 5.6,
      "invalidation_price": 0.779172,
      "expires_at": null,
      "math": {
        "hurst": 0.5,
        "hurst_interpretation": "数据不足(需≥100)",
        "entropy_predictability": 0.2553,
        "kelly_fraction": 0.125,
        "monte_carlo_bull_prob": 0.336,
        "monte_carlo_bear_prob": 0.664,
        "monte_carlo_var95": -39.98,
        "vol_regime": "normal",
        "vol_percentile": 51.3,
        "market_regime": "trending_down",
        "market_regime_confidence": 1.0,
        "math_score_adjustment": -35.0,
        "math_confidence": 0.543,
        "key_findings": [
          "MC上涨概率仅34%，方向存疑",
          "VaR(95%)=-40.0%，尾部风险大"
        ]
      },
      "strategy": {
        "strategy_version": 1,
        "regime": "trending_down",
        "adaptive_weights": {
          "bigorder_anomaly": 0.3196,
          "quantitative": 0.3516,
          "technical": 0.3288
        },
        "global_win_rate": 0.5,
        "evolution_count": 0
      },
      "status": "pending",
      "created_at": "2026-06-10 15:18:13",
      "updated_at": "",
      "settled_at": null,
      "settled_price": null,
      "pnl_pct": null
    },
    {
      "id": null,
      "coin": "ARB",
      "direction": "short",
      "grade": "A",
      "current_price": 0.08,
      "entry_low": 0.07964,
      "entry_high": 0.08036,
      "stop_loss": 0.081802,
      "take_profit": 0.076997,
      "risk_reward_ratio": 1.7,
      "confidence": 84.5,
      "sources": [
        {
          "name": "bigorder_anomaly",
          "score": 55.0986889454472,
          "direction": "short",
          "weight": 0.3398,
          "detail": "12h聚合(Binance+Bybit+Bitget), 买$48K/卖$81K, 净流入$-32K, 600笔大单"
        },
        {
          "name": "quantitative",
          "score": 11.0,
          "direction": "short",
          "weight": 0.3516,
          "detail": "综合评分-11, 强度弱, 置信度50.0%"
        },
        {
          "name": "technical",
          "score": 20.0,
          "direction": "short",
          "weight": 0.3288,
          "detail": "EMA空头排列(9<21<55), ADX=40趋势强+DI空头, RSI=21严重超卖, RSI底背离, MACD死叉+零轴下方, BB下轨(3%), Supertrend空头"
        }
      ],
      "win_rate": null,
      "sample_count": null,
      "avg_profit_pct": null,
      "position_pct": 5.6,
      "invalidation_price": 0.081802,
      "expires_at": null,
      "math": {
        "hurst": 0.5,
        "hurst_interpretation": "数据不足(需≥100)",
        "entropy_predictability": 0.2546,
        "kelly_fraction": 0.125,
        "monte_carlo_bull_prob": 0.157,
        "monte_carlo_bear_prob": 0.843,
        "monte_carlo_var95": -38.88,
        "vol_regime": "normal",
        "vol_percentile": 33.3,
        "market_regime": "trending_down",
        "market_regime_confidence": 1.0,
        "math_score_adjustment": -35.0,
        "math_confidence": 0.543,
        "key_findings": [
          "MC上涨概率仅16%，方向存疑",
          "VaR(95%)=-38.9%，尾部风险大"
        ]
      },
      "strategy": {
        "strategy_version": 1,
        "regime": "trending_down",
        "adaptive_weights": {
          "bigorder_anomaly": 0.3196,
          "quantitative": 0.3516,
          "technical": 0.3288
        },
        "global_win_rate": 0.5,
        "evolution_count": 0
      },
      "status": "pending",
      "created_at": "2026-06-10 15:18:57",
      "updated_at": "",
      "settled_at": null,
      "settled_price": null,
      "pnl_pct": null
    },
    {
      "id": null,
      "coin": "ICP",
      "direction": "short",
      "grade": "A",
      "current_price": 2.27,
      "entry_low": 2.2591,
      "entry_high": 2.2809,
      "stop_loss": 2.3245,
      "take_profit": 2.1791,
      "risk_reward_ratio": 1.7,
      "confidence": 84.5,
      "sources": [
        {
          "name": "bigorder_anomaly",
          "score": 50.01690362337728,
          "direction": "short",
          "weight": 0.3398,
          "detail": "12h聚合(Binance+Bybit+Bitget), 买$44K/卖$66K, 净流入$-22K, 600笔大单"
        },
        {
          "name": "quantitative",
          "score": 10.0,
          "direction": "short",
          "weight": 0.3516,
          "detail": "综合评分-10, 强度弱, 置信度50.0%"
        },
        {
          "name": "technical",
          "score": 15.0,
          "direction": "short",
          "weight": 0.3288,
          "detail": "短期EMA偏空, RSI=37偏弱, MACD死叉+零轴下方, BB下轨(4%), Supertrend多头"
        }
      ],
      "win_rate": null,
      "sample_count": null,
      "avg_profit_pct": null,
      "position_pct": 5.6,
      "invalidation_price": 2.3245,
      "expires_at": null,
      "math": {
        "hurst": 0.5,
        "hurst_interpretation": "数据不足(需≥100)",
        "entropy_predictability": 0.2791,
        "kelly_fraction": 0.125,
        "monte_carlo_bull_prob": 0.388,
        "monte_carlo_bear_prob": 0.612,
        "monte_carlo_var95": -43.35,
        "vol_regime": "normal",
        "vol_percentile": 66.7,
        "market_regime": "trending_down",
        "market_regime_confidence": 1.0,
        "math_score_adjustment": -35.0,
        "math_confidence": 0.547,
        "key_findings": [
          "MC上涨概率仅39%，方向存疑",
          "VaR(95%)=-43.4%，尾部风险大"
        ]
      },
      "strategy": {
        "strategy_version": 1,
        "regime": "trending_down",
        "adaptive_weights": {
          "bigorder_anomaly": 0.3196,
          "quantitative": 0.3516,
          "technical": 0.3288
        },
        "global_win_rate": 0.5,
        "evolution_count": 0
      },
      "status": "pending",
      "created_at": "2026-06-10 15:19:39",
      "updated_at": "",
      "settled_at": null,
      "settled_price": null,
      "pnl_pct": null
    },
    {
      "id": null,
      "coin": "DOGE",
      "direction": "short",
      "grade": "A",
      "current_price": 0.08,
      "entry_low": 0.07964,
      "entry_high": 0.08036,
      "stop_loss": 0.0818,
      "take_profit": 0.077,
      "risk_reward_ratio": 1.7,
      "confidence": 80.0,
      "sources": [
        {
          "name": "bigorder_anomaly",
          "score": 61.71933857377242,
          "direction": "short",
          "weight": 0.3398,
          "detail": "12h聚合(Binance+Bybit+Bitget), 买$50K/卖$96K, 净流入$-46K, 600笔大单"
        },
        {
          "name": "quantitative",
          "score": 8.0,
          "direction": "neutral",
          "weight": 0.3516,
          "detail": "综合评分-8, 强度无, 置信度48.0%"
        },
        {
          "name": "technical",
          "score": 20.0,
          "direction": "short",
          "weight": 0.3288,
          "detail": "EMA空头排列(9<21<55), ADX=41趋势强+DI空头, RSI=23严重超卖, RSI底背离, MACD死叉+零轴下方, BB下轨(-5%), Supertrend空头"
        }
      ],
      "win_rate": null,
      "sample_count": null,
      "avg_profit_pct": null,
      "position_pct": 5.6,
      "invalidation_price": 0.0818,
      "expires_at": null,
      "math": {
        "hurst": 0.5,
        "hurst_interpretation": "数据不足(需≥100)",
        "entropy_predictability": 0.2414,
        "kelly_fraction": 0.125,
        "monte_carlo_bull_prob": 0.301,
        "monte_carlo_bear_prob": 0.699,
        "monte_carlo_var95": -27.04,
        "vol_regime": "normal",
        "vol_percentile": 51.3,
        "market_regime": "trending_down",
        "market_regime_confidence": 1.0,
        "math_score_adjustment": -50.0,
        "math_confidence": 0.541,
        "key_findings": [
          "可预测性24%过低，噪音主导",
          "MC上涨概率仅30%，方向存疑",
          "VaR(95%)=-27.0%，尾部风险大"
        ]
      },
      "strategy": {
        "strategy_version": 1,
        "regime": "trending_down",
        "adaptive_weights": {
          "bigorder_anomaly": 0.3196,
          "quantitative": 0.3516,
          "technical": 0.3288
        },
        "global_win_rate": 0.5,
        "evolution_count": 0
      },
      "status": "pending",
      "created_at": "2026-06-10 15:13:15",
      "updated_at": "",
      "settled_at": null,
      "settled_price": null,
      "pnl_pct": null
    },
    {
      "id": null,
      "coin": "XRP",
      "direction": "short",
      "grade": "A",
      "current_price": 1.12,
      "entry_low": 1.115,
      "entry_high": 1.125,
      "stop_loss": 1.1452,
      "take_profit": 1.078,
      "risk_reward_ratio": 1.7,
      "confidence": 80.0,
      "sources": [
        {
          "name": "bigorder_anomaly",
          "score": 50.85732062936654,
          "direction": "short",
          "weight": 0.3398,
          "detail": "12h聚合(Binance+Bybit+Bitget), 买$147K/卖$225K, 净流入$-78K, 600笔大单"
        },
        {
          "name": "quantitative",
          "score": 16.0,
          "direction": "short",
          "weight": 0.3516,
          "detail": "综合评分-16, 强度弱, 置信度50.0%"
        },
        {
          "name": "technical",
          "score": 45.0,
          "direction": "short",
          "weight": 0.3288,
          "detail": "EMA空头排列(9<21<55), ADX=36趋势强+DI空头, RSI=27超卖区, MACD死叉+零轴下方, BB下轨(3%), Supertrend空头"
        }
      ],
      "win_rate": null,
      "sample_count": null,
      "avg_profit_pct": null,
      "position_pct": 5.6,
      "invalidation_price": 1.1452,
      "expires_at": null,
      "math": {
        "hurst": 0.5,
        "hurst_interpretation": "数据不足(需≥100)",
        "entropy_predictability": 0.132,
        "kelly_fraction": 0.125,
        "monte_carlo_bull_prob": 0.217,
        "monte_carlo_bear_prob": 0.783,
        "monte_carlo_var95": -23.58,
        "vol_regime": "normal",
        "vol_percentile": 74.4,
        "market_regime": "trending_down",
        "market_regime_confidence": 1.0,
        "math_score_adjustment": -50.0,
        "math_confidence": 0.525,
        "key_findings": [
          "可预测性13%过低，噪音主导",
          "MC上涨概率仅22%，方向存疑",
          "VaR(95%)=-23.6%，尾部风险大"
        ]
      },
      "strategy": {
        "strategy_version": 1,
        "regime": "trending_down",
        "adaptive_weights": {
          "bigorder_anomaly": 0.3196,
          "quantitative": 0.3516,
          "technical": 0.3288
        },
        "global_win_rate": 0.5,
        "evolution_count": 0
      },
      "status": "pending",
      "created_at": "2026-06-10 15:13:24",
      "updated_at": "",
      "settled_at": null,
      "settled_price": null,
      "pnl_pct": null
    },
    {
      "id": null,
      "coin": "PEPE",
      "direction": "short",
      "grade": "A",
      "current_price": 2.85e-06,
      "entry_low": 2.836892e-06,
      "entry_high": 2.863108e-06,
      "stop_loss": 2.91554e-06,
      "take_profit": 2.740767e-06,
      "risk_reward_ratio": 1.7,
      "confidence": 80.0,
      "sources": [
        {
          "name": "bigorder_anomaly",
          "score": 56.290416205601815,
          "direction": "short",
          "weight": 0.3398,
          "detail": "12h聚合(Binance+Bybit+Bitget), 买$99K/卖$169K, 净流入$-71K, 600笔大单"
        },
        {
          "name": "quantitative",
          "score": 14.0,
          "direction": "short",
          "weight": 0.3516,
          "detail": "综合评分-14, 强度弱, 置信度50.0%"
        },
        {
          "name": "technical",
          "score": 25.0,
          "direction": "short",
          "weight": 0.3288,
          "detail": "EMA空头排列(9<21<55), ADX=41趋势强+DI空头, RSI=23严重超卖, MACD死叉+零轴下方, Supertrend多头"
        }
      ],
      "win_rate": null,
      "sample_count": null,
      "avg_profit_pct": null,
      "position_pct": 5.6,
      "invalidation_price": 2.91554e-06,
      "expires_at": null,
      "math": {
        "hurst": 0.5,
        "hurst_interpretation": "数据不足(需≥100)",
        "entropy_predictability": 0.1064,
        "kelly_fraction": 0.125,
        "monte_carlo_bull_prob": 0.18,
        "monte_carlo_bear_prob": 0.82,
        "monte_carlo_var95": -30.65,
        "vol_regime": "normal",
        "vol_percentile": 53.8,
        "market_regime": "trending_down",
        "market_regime_confidence": 1.0,
        "math_score_adjustment": -50.0,
        "math_confidence": 0.521,
        "key_findings": [
          "可预测性11%过低，噪音主导",
          "MC上涨概率仅18%，方向存疑",
          "VaR(95%)=-30.6%，尾部风险大"
        ]
      },
      "strategy": {
        "strategy_version": 1,
        "regime": "trending_down",
        "adaptive_weights": {
          "bigorder_anomaly": 0.3196,
          "quantitative": 0.3516,
          "technical": 0.3288
        },
        "global_win_rate": 0.5,
        "evolution_count": 0
      },
      "status": "pending",
      "created_at": "2026-06-10 15:14:59",
      "updated_at": "",
      "settled_at": null,
      "settled_price": null,
      "pnl_pct": null
    },
    {
      "id": null,
      "coin": "ENA",
      "direction": "short",
      "grade": "A",
      "current_price": 0.08,
      "entry_low": 0.079443,
      "entry_high": 0.0804,
      "stop_loss": 0.082784,
      "take_profit": 0.07536,
      "risk_reward_ratio": 1.7,
      "confidence": 74.0,
      "sources": [
        {
          "name": "bigorder_anomaly",
          "score": 45.815725689741626,
          "direction": "short",
          "weight": 0.3398,
          "detail": "12h聚合(Binance+Bybit+Bitget), 买$88K/卖$120K, 净流入$-33K, 599笔大单"
        },
        {
          "name": "quantitative",
          "score": 10.75,
          "direction": "short",
          "weight": 0.3516,
          "detail": "综合评分-11, 强度弱, 置信度50.0%"
        },
        {
          "name": "technical",
          "score": 25.0,
          "direction": "short",
          "weight": 0.3288,
          "detail": "EMA空头排列(9<21<55), ADX=17震荡市, RSI=35偏弱, RSI底背离, MACD死叉+零轴下方, MACD底背离, BB下轨(-3%), Supertrend空头"
        }
      ],
      "win_rate": null,
      "sample_count": null,
      "avg_profit_pct": null,
      "position_pct": 5.6,
      "invalidation_price": 0.082784,
      "expires_at": null,
      "math": {
        "hurst": 0.5,
        "hurst_interpretation": "数据不足(需≥100)",
        "entropy_predictability": 0.228,
        "kelly_fraction": 0.125,
        "monte_carlo_bull_prob": 0.339,
        "monte_carlo_bear_prob": 0.661,
        "monte_carlo_var95": -44.24,
        "vol_regime": "extreme",
        "vol_percentile": 100.0,
        "market_regime": "trending_down",
        "market_regime_confidence": 0.5,
        "math_score_adjustment": -70.0,
        "math_confidence": 0.439,
        "key_findings": [
          "可预测性23%过低，噪音主导",
          "MC上涨概率仅34%，方向存疑",
          "VaR(95%)=-44.2%，尾部风险大",
          "波动率极端(P100)，建议降仓"
        ]
      },
      "strategy": {
        "strategy_version": 1,
        "regime": "trending_down",
        "adaptive_weights": {
          "bigorder_anomaly": 0.3196,
          "quantitative": 0.3516,
          "technical": 0.3288
        },
        "global_win_rate": 0.5,
        "evolution_count": 0
      },
      "status": "pending",
      "created_at": "2026-06-10 15:14:46",
      "updated_at": "",
      "settled_at": null,
      "settled_price": null,
      "pnl_pct": null
    },
    {
      "id": null,
      "coin": "PUMP",
      "direction": "short",
      "grade": "A",
      "current_price": 0.001628,
      "entry_low": 0.00162,
      "entry_high": 0.001636,
      "stop_loss": 0.001669,
      "take_profit": 0.00156,
      "risk_reward_ratio": 1.7,
      "confidence": 74.0,
      "sources": [
        {
          "name": "bigorder_anomaly",
          "score": 18.788805496409687,
          "direction": "neutral",
          "weight": 0.3398,
          "detail": "12h聚合(Binance+Bybit+Bitget), 买$51K/卖$59K, 净流入$-8K, 600笔大单"
        },
        {
          "name": "quantitative",
          "score": 18.25,
          "direction": "short",
          "weight": 0.3516,
          "detail": "综合评分-18, 强度弱, 置信度50.0%"
        },
        {
          "name": "technical",
          "score": 40.0,
          "direction": "short",
          "weight": 0.3288,
          "detail": "EMA空头排列(9<21<55), ADX=14震荡市, RSI=41偏弱, MACD死叉+零轴下方, Supertrend多头"
        }
      ],
      "win_rate": null,
      "sample_count": null,
      "avg_profit_pct": null,
      "position_pct": 5.6,
      "invalidation_price": 0.001669,
      "expires_at": null,
      "math": {
        "hurst": 0.5,
        "hurst_interpretation": "数据不足(需≥100)",
        "entropy_predictability": 0.1667,
        "kelly_fraction": 0.125,
        "monte_carlo_bull_prob": 0.322,
        "monte_carlo_bear_prob": 0.678,
        "monte_carlo_var95": -34.72,
        "vol_regime": "extreme",
        "vol_percentile": 100.0,
        "market_regime": "trending_down",
        "market_regime_confidence": 0.5,
        "math_score_adjustment": -70.0,
        "math_confidence": 0.43,
        "key_findings": [
          "可预测性17%过低，噪音主导",
          "MC上涨概率仅32%，方向存疑",
          "VaR(95%)=-34.7%，尾部风险大",
          "波动率极端(P100)，建议降仓"
        ]
      },
      "strategy": {
        "strategy_version": 1,
        "regime": "trending_down",
        "adaptive_weights": {
          "bigorder_anomaly": 0.3196,
          "quantitative": 0.3516,
          "technical": 0.3288
        },
        "global_win_rate": 0.5,
        "evolution_count": 0
      },
      "status": "pending",
      "created_at": "2026-06-10 15:17:49",
      "updated_at": "",
      "settled_at": null,
      "settled_price": null,
      "pnl_pct": null
    },
    {
      "id": null,
      "coin": "SEI",
      "direction": "short",
      "grade": "A",
      "current_price": 0.05,
      "entry_low": 0.049723,
      "entry_high": 0.05025,
      "stop_loss": 0.051386,
      "take_profit": 0.047691,
      "risk_reward_ratio": 1.7,
      "confidence": 74.0,
      "sources": [
        {
          "name": "bigorder_anomaly",
          "score": 42.17645913154896,
          "direction": "short",
          "weight": 0.3398,
          "detail": "12h聚合(Binance+Bybit+Bitget), 买$20K/卖$25K, 净流入$-5K, 600笔大单"
        },
        {
          "name": "quantitative",
          "score": 10.75,
          "direction": "short",
          "weight": 0.3516,
          "detail": "综合评分-11, 强度弱, 置信度50.0%"
        },
        {
          "name": "technical",
          "score": 10.0,
          "direction": "short",
          "weight": 0.3288,
          "detail": "EMA空头排列(9<21<55), RSI=32超卖区, MACD死叉+零轴下方, BB下轨(9%), Supertrend多头"
        }
      ],
      "win_rate": null,
      "sample_count": null,
      "avg_profit_pct": null,
      "position_pct": 5.6,
      "invalidation_price": 0.051386,
      "expires_at": null,
      "math": {
        "hurst": 0.5,
        "hurst_interpretation": "数据不足(需≥100)",
        "entropy_predictability": 0.1679,
        "kelly_fraction": 0.125,
        "monte_carlo_bull_prob": 0.379,
        "monte_carlo_bear_prob": 0.621,
        "monte_carlo_var95": -35.59,
        "vol_regime": "extreme",
        "vol_percentile": 97.4,
        "market_regime": "trending_down",
        "market_regime_confidence": 0.5,
        "math_score_adjustment": -70.0,
        "math_confidence": 0.43,
        "key_findings": [
          "可预测性17%过低，噪音主导",
          "MC上涨概率仅38%，方向存疑",
          "VaR(95%)=-35.6%，尾部风险大",
          "波动率极端(P97)，建议降仓"
        ]
      },
      "strategy": {
        "strategy_version": 1,
        "regime": "trending_down",
        "adaptive_weights": {
          "bigorder_anomaly": 0.3196,
          "quantitative": 0.3516,
          "technical": 0.3288
        },
        "global_win_rate": 0.5,
        "evolution_count": 0
      },
      "status": "pending",
      "created_at": "2026-06-10 15:22:37",
      "updated_at": "",
      "settled_at": null,
      "settled_price": null,
      "pnl_pct": null
    }
  ],
  "displays": [
    {
      "type": "signalCard",
      "data": {
        "displayText": "📊 TON 交易信号卡 | 🟡A级 | 置信度 95%\n├─ 方向：做空\n├─ 当前价格：$1.67\n├─ 进场区间：$1.66 - $1.68\n├─ 止损：$1.72 (+2.9%)\n├─ 止盈：$1.57 (-5.9%)\n├─ 盈亏比：2.0 : 1\n├─ 建议仓位：总资金 6%（经风险调整后的实际仓位）\n├─ Kelly 仓位：12.5%（理论最优仓位，建议仓位取其半值防回撤）\n├─ 依据：大单异动(61) + 量化六因子(2) + 技术分析(10)\n├─ 数学推导：Hurst=0.50 | MC 看跌51% | 波动率=normal | 市场=trending_up | Kelly=12.5%\n│  · VaR(95%)=-45.8%，尾部风险大\n│  · 市场状态=trending_up，与信号方向一致\n├─ 历史胜率：--（近30天 -- 次）\n├─ 平均盈利：--\n├─ 策略v1 | trending_up | 全局胜率50%\n└─ 失效条件：突破 $1.72",
        "kellyPct": 12.5,
        "card": {
          "coin": "TON",
          "direction": "short",
          "grade": "A",
          "confidence": 95.0,
          "currentPrice": 1.67,
          "entryZone": [
            1.6602,
            1.6783
          ],
          "stopLoss": 1.7191,
          "takeProfit": 1.5718,
          "riskReward": 2.0,
          "positionPct": 6,
          "kellyPct": 12.5,
          "invalidation": 1.7191,
          "sources": [
            {
              "name": "bigorder_anomaly",
              "score": 61
            },
            {
              "name": "quantitative",
              "score": 2
            },
            {
              "name": "technical",
              "score": 10
            }
          ],
          "winRate": null,
          "sampleCount": null,
          "avgProfit": null
        },
        "math": {
          "hurst": 0.5,
          "mcBullProb": 0.486,
          "volatility": "normal",
          "marketRegime": "trending_up"
        },
        "strategy": {
          "version": 1,
          "regime": "trending_up",
          "globalWinRate": 0.5
        }
      }
    },
    {
      "type": "signalCard",
      "data": {
        "displayText": "📊 SENT 交易信号卡 | 🟡A级 | 置信度 95%\n├─ 方向：做空\n├─ 当前价格：$0.0200\n├─ 进场区间：$0.0196 - $0.0201\n├─ 止损：$0.0219 (+9.6%)\n├─ 止盈：$0.0162 (-19.1%)\n├─ 盈亏比：2.0 : 1\n├─ 建议仓位：总资金 6%（经风险调整后的实际仓位）\n├─ Kelly 仓位：12.5%（理论最优仓位，建议仓位取其半值防回撤）\n├─ 依据：大单异动(46) + 量化六因子(25) + 技术分析(52)\n├─ 数学推导：Hurst=0.50 | MC 看跌46% | 波动率=normal | 市场=trending_up | Kelly=12.5%\n│  · VaR(95%)=-35.6%，尾部风险大\n│  · 市场状态=trending_up，与信号方向一致\n├─ 历史胜率：--（近30天 -- 次）\n├─ 平均盈利：--\n├─ 策略v1 | trending_up | 全局胜率50%\n└─ 失效条件：突破 $0.0219",
        "kellyPct": 12.5,
        "card": {
          "coin": "SENT",
          "direction": "short",
          "grade": "A",
          "confidence": 95.0,
          "currentPrice": 0.02,
          "entryZone": [
            0.019617,
            0.0201
          ],
          "stopLoss": 0.021915,
          "takeProfit": 0.01617,
          "riskReward": 2.0,
          "positionPct": 6,
          "kellyPct": 12.5,
          "invalidation": 0.021915,
          "sources": [
            {
              "name": "bigorder_anomaly",
              "score": 46
            },
            {
              "name": "quantitative",
              "score": 25
            },
            {
              "name": "technical",
              "score": 52
            }
          ],
          "winRate": null,
          "sampleCount": null,
          "avgProfit": null
        },
        "math": {
          "hurst": 0.5,
          "mcBullProb": 0.535,
          "volatility": "normal",
          "marketRegime": "trending_up"
        },
        "strategy": {
          "version": 1,
          "regime": "trending_up",
          "globalWinRate": 0.5
        }
      }
    },
    {
      "type": "signalCard",
      "data": {
        "displayText": "📊 STG 交易信号卡 | 🟡A级 | 置信度 95%\n├─ 方向：做多\n├─ 当前价格：$0.3900\n├─ 进场区间：$0.3881 - $0.3972\n├─ 止损：$0.3541 (-9.2%)\n├─ 止盈：$0.4619 (+18.4%)\n├─ 盈亏比：2.0 : 1\n├─ 建议仓位：总资金 6%（经风险调整后的实际仓位）\n├─ Kelly 仓位：12.5%（理论最优仓位，建议仓位取其半值防回撤）\n├─ 依据：大单异动(75) + 量化六因子(2) + 技术分析(30)\n├─ 数学推导：Hurst=0.50 | MC 看涨58% | 波动率=extreme | 市场=trending_up | Kelly=12.5%\n│  · 可预测性51%，信号可靠性高\n│  · VaR(95%)=-55.6%，尾部风险大\n│  · 波动率极端(P100)，建议降仓\n├─ 历史胜率：--（近30天 -- 次）\n├─ 平均盈利：--\n├─ 策略v1 | trending_up | 全局胜率50%\n└─ 失效条件：跌破 $0.3541",
        "kellyPct": 12.5,
        "card": {
          "coin": "STG",
          "direction": "long",
          "grade": "A",
          "confidence": 95.0,
          "currentPrice": 0.39,
          "entryZone": [
            0.38805,
            0.397189
          ],
          "stopLoss": 0.354055,
          "takeProfit": 0.461891,
          "riskReward": 2.0,
          "positionPct": 6,
          "kellyPct": 12.5,
          "invalidation": 0.354055,
          "sources": [
            {
              "name": "bigorder_anomaly",
              "score": 75
            },
            {
              "name": "quantitative",
              "score": 2
            },
            {
              "name": "technical",
              "score": 30
            }
          ],
          "winRate": null,
          "sampleCount": null,
          "avgProfit": null
        },
        "math": {
          "hurst": 0.5,
          "mcBullProb": 0.578,
          "volatility": "extreme",
          "marketRegime": "trending_up"
        },
        "strategy": {
          "version": 1,
          "regime": "trending_up",
          "globalWinRate": 0.5
        }
      }
    },
    {
      "type": "signalCard",
      "data": {
        "displayText": "📊 JTO 交易信号卡 | 🔴S级 | 置信度 95%\n├─ 方向：做多\n├─ 当前价格：$0.6100\n├─ 进场区间：$0.6069 - $0.6160\n├─ 止损：$0.5798 (-5.0%)\n├─ 止盈：$0.6704 (+9.9%)\n├─ 盈亏比：2.0 : 1\n├─ 建议仓位：总资金 9%（经风险调整后的实际仓位）\n├─ Kelly 仓位：12.5%（理论最优仓位，建议仓位取其半值防回撤）\n├─ 依据：大单异动(55) + 量化六因子(19) + 技术分析(47)\n├─ 数学推导：Hurst=0.50 | MC 看涨67% | 波动率=normal | 市场=trending_up | Kelly=12.5%\n│  · MC上涨概率67%，方向确认\n│  · VaR(95%)=-41.5%，尾部风险大\n│  · 市场状态=trending_up，与信号方向一致\n├─ 历史胜率：--（近30天 -- 次）\n├─ 平均盈利：--\n├─ 策略v1 | trending_up | 全局胜率50%\n└─ 失效条件：跌破 $0.5798",
        "kellyPct": 12.5,
        "card": {
          "coin": "JTO",
          "direction": "long",
          "grade": "S",
          "confidence": 95.0,
          "currentPrice": 0.61,
          "entryZone": [
            0.60695,
            0.616041
          ],
          "stopLoss": 0.579793,
          "takeProfit": 0.670415,
          "riskReward": 2.0,
          "positionPct": 9,
          "kellyPct": 12.5,
          "invalidation": 0.579793,
          "sources": [
            {
              "name": "bigorder_anomaly",
              "score": 55
            },
            {
              "name": "quantitative",
              "score": 19
            },
            {
              "name": "technical",
              "score": 47
            }
          ],
          "winRate": null,
          "sampleCount": null,
          "avgProfit": null
        },
        "math": {
          "hurst": 0.5,
          "mcBullProb": 0.673,
          "volatility": "normal",
          "marketRegime": "trending_up"
        },
        "strategy": {
          "version": 1,
          "regime": "trending_up",
          "globalWinRate": 0.5
        }
      }
    },
    {
      "type": "signalCard",
      "data": {
        "displayText": "📊 ONDO 交易信号卡 | 🟡A级 | 置信度 94%\n├─ 方向：做空\n├─ 当前价格：$0.3500\n├─ 进场区间：$0.3475 - $0.3518\n├─ 止损：$0.3627 (+3.6%)\n├─ 止盈：$0.3288 (-6.0%)\n├─ 盈亏比：1.7 : 1\n├─ 建议仓位：总资金 6%（经风险调整后的实际仓位）\n├─ Kelly 仓位：12.5%（理论最优仓位，建议仓位取其半值防回撤）\n├─ 依据：大单异动(51) + 量化六因子(18) + 技术分析(35)\n├─ 数学推导：Hurst=0.50 | MC 看跌39% | 波动率=normal | 市场=trending_down | Kelly=12.5%\n│  · 可预测性22%过低，噪音主导\n│  · MC上涨概率61%，方向确认\n│  · VaR(95%)=-33.9%，尾部风险大\n├─ 历史胜率：--（近30天 -- 次）\n├─ 平均盈利：--\n├─ 策略v1 | trending_down | 全局胜率50%\n└─ 失效条件：突破 $0.3627",
        "kellyPct": 12.5,
        "card": {
          "coin": "ONDO",
          "direction": "short",
          "grade": "A",
          "confidence": 93.5,
          "currentPrice": 0.35,
          "entryZone": [
            0.347462,
            0.35175
          ],
          "stopLoss": 0.362691,
          "takeProfit": 0.328848,
          "riskReward": 1.7,
          "positionPct": 6,
          "kellyPct": 12.5,
          "invalidation": 0.362691,
          "sources": [
            {
              "name": "bigorder_anomaly",
              "score": 51
            },
            {
              "name": "quantitative",
              "score": 18
            },
            {
              "name": "technical",
              "score": 35
            }
          ],
          "winRate": null,
          "sampleCount": null,
          "avgProfit": null
        },
        "math": {
          "hurst": 0.5,
          "mcBullProb": 0.612,
          "volatility": "normal",
          "marketRegime": "trending_down"
        },
        "strategy": {
          "version": 1,
          "regime": "trending_down",
          "globalWinRate": 0.5
        }
      }
    },
    {
      "type": "signalCard",
      "data": {
        "displayText": "📊 TIA 交易信号卡 | 🟡A级 | 置信度 94%\n├─ 方向：做空\n├─ 当前价格：$0.3200\n├─ 进场区间：$0.3181 - $0.3216\n├─ 止损：$0.3297 (+3.0%)\n├─ 止盈：$0.3005 (-6.1%)\n├─ 盈亏比：2.0 : 1\n├─ 建议仓位：总资金 6%（经风险调整后的实际仓位）\n├─ Kelly 仓位：12.5%（理论最优仓位，建议仓位取其半值防回撤）\n├─ 依据：大单异动(51) + 量化六因子(12) + 技术分析(35)\n├─ 数学推导：Hurst=0.50 | MC 看跌53% | 波动率=normal | 市场=trending_up | Kelly=12.5%\n│  · 可预测性24%过低，噪音主导\n│  · VaR(95%)=-38.3%，尾部风险大\n│  · 市场状态=trending_up，与信号方向一致\n├─ 历史胜率：--（近30天 -- 次）\n├─ 平均盈利：--\n├─ 策略v1 | trending_up | 全局胜率50%\n└─ 失效条件：突破 $0.3297",
        "kellyPct": 12.5,
        "card": {
          "coin": "TIA",
          "direction": "short",
          "grade": "A",
          "confidence": 93.5,
          "currentPrice": 0.32,
          "entryZone": [
            0.318051,
            0.3216
          ],
          "stopLoss": 0.329746,
          "takeProfit": 0.300509,
          "riskReward": 2.0,
          "positionPct": 6,
          "kellyPct": 12.5,
          "invalidation": 0.329746,
          "sources": [
            {
              "name": "bigorder_anomaly",
              "score": 51
            },
            {
              "name": "quantitative",
              "score": 12
            },
            {
              "name": "technical",
              "score": 35
            }
          ],
          "winRate": null,
          "sampleCount": null,
          "avgProfit": null
        },
        "math": {
          "hurst": 0.5,
          "mcBullProb": 0.474,
          "volatility": "normal",
          "marketRegime": "trending_up"
        },
        "strategy": {
          "version": 1,
          "regime": "trending_up",
          "globalWinRate": 0.5
        }
      }
    },
    {
      "type": "signalCard",
      "data": {
        "displayText": "📊 IO 交易信号卡 | 🟡A级 | 置信度 92%\n├─ 方向：做多\n├─ 当前价格：$0.1700\n├─ 进场区间：$0.1691 - $0.1722\n├─ 止损：$0.1554 (-8.6%)\n├─ 止盈：$0.1846 (+8.6%)\n├─ 盈亏比：1.0 : 1\n├─ 建议仓位：总资金 6%（经风险调整后的实际仓位）\n├─ Kelly 仓位：12.5%（理论最优仓位，建议仓位取其半值防回撤）\n├─ 依据：大单异动(46) + 量化六因子(6) + 技术分析(12)\n├─ 数学推导：Hurst=0.50 | MC 看涨55% | 波动率=normal | 市场=mean_reverting | Kelly=12.5%\n│  · VaR(95%)=-56.2%，尾部风险大\n├─ 历史胜率：--（近30天 -- 次）\n├─ 平均盈利：--\n├─ 策略v1 | mean_reverting | 全局胜率50%\n└─ 失效条件：跌破 $0.1554",
        "kellyPct": 12.5,
        "card": {
          "coin": "IO",
          "direction": "long",
          "grade": "A",
          "confidence": 92.0,
          "currentPrice": 0.17,
          "entryZone": [
            0.16915,
            0.172184
          ],
          "stopLoss": 0.155438,
          "takeProfit": 0.184562,
          "riskReward": 1.0,
          "positionPct": 6,
          "kellyPct": 12.5,
          "invalidation": 0.155438,
          "sources": [
            {
              "name": "bigorder_anomaly",
              "score": 46
            },
            {
              "name": "quantitative",
              "score": 6
            },
            {
              "name": "technical",
              "score": 12
            }
          ],
          "winRate": null,
          "sampleCount": null,
          "avgProfit": null
        },
        "math": {
          "hurst": 0.5,
          "mcBullProb": 0.546,
          "volatility": "normal",
          "marketRegime": "mean_reverting"
        },
        "strategy": {
          "version": 1,
          "regime": "mean_reverting",
          "globalWinRate": 0.5
        }
      }
    },
    {
      "type": "signalCard",
      "data": {
        "displayText": "📊 BIO 交易信号卡 | 🟡A级 | 置信度 92%\n├─ 方向：做空\n├─ 当前价格：$0.0300\n├─ 进场区间：$0.0298 - $0.0301\n├─ 止损：$0.0312 (+4.1%)\n├─ 止盈：$0.0279 (-6.9%)\n├─ 盈亏比：1.7 : 1\n├─ 建议仓位：总资金 6%（经风险调整后的实际仓位）\n├─ Kelly 仓位：12.5%（理论最优仓位，建议仓位取其半值防回撤）\n├─ 依据：大单异动(52) + 量化六因子(33) + 技术分析(45)\n├─ 数学推导：Hurst=0.50 | MC 看跌50% | 波动率=normal | 市场=trending_down | Kelly=12.5%\n│  · VaR(95%)=-65.4%，尾部风险大\n├─ 历史胜率：--（近30天 -- 次）\n├─ 平均盈利：--\n├─ 策略v1 | trending_down | 全局胜率50%\n└─ 失效条件：突破 $0.0312",
        "kellyPct": 12.5,
        "card": {
          "coin": "BIO",
          "direction": "short",
          "grade": "A",
          "confidence": 92.0,
          "currentPrice": 0.03,
          "entryZone": [
            0.029752,
            0.03015
          ],
          "stopLoss": 0.031238,
          "takeProfit": 0.027937,
          "riskReward": 1.7,
          "positionPct": 6,
          "kellyPct": 12.5,
          "invalidation": 0.031238,
          "sources": [
            {
              "name": "bigorder_anomaly",
              "score": 52
            },
            {
              "name": "quantitative",
              "score": 33
            },
            {
              "name": "technical",
              "score": 45
            }
          ],
          "winRate": null,
          "sampleCount": null,
          "avgProfit": null
        },
        "math": {
          "hurst": 0.5,
          "mcBullProb": 0.504,
          "volatility": "normal",
          "marketRegime": "trending_down"
        },
        "strategy": {
          "version": 1,
          "regime": "trending_down",
          "globalWinRate": 0.5
        }
      }
    },
    {
      "type": "signalCard",
      "data": {
        "displayText": "📊 SAHARA 交易信号卡 | 🟡A级 | 置信度 88%\n├─ 方向：做空\n├─ 当前价格：$0.0200\n├─ 进场区间：$0.0196 - $0.0201\n├─ 止损：$0.0216 (+8.2%)\n├─ 止盈：$0.0152 (-23.9%)\n├─ 盈亏比：2.9 : 1\n├─ 建议仓位：总资金 6%（经风险调整后的实际仓位）\n├─ Kelly 仓位：12.5%（理论最优仓位，建议仓位取其半值防回撤）\n├─ 依据：大单异动(51) + 量化六因子(2) + 技术分析(10)\n├─ 数学推导：Hurst=0.50 | MC 看跌63% | 波动率=low | 市场=quiet | Kelly=12.5%\n│  · MC上涨概率仅37%，方向存疑\n│  · VaR(95%)=-68.7%，尾部风险大\n│  · 波动率低位(P18)，趋势可靠\n├─ 历史胜率：--（近30天 -- 次）\n├─ 平均盈利：--\n├─ 策略v1 | quiet | 全局胜率50%\n└─ 失效条件：突破 $0.0216",
        "kellyPct": 12.5,
        "card": {
          "coin": "SAHARA",
          "direction": "short",
          "grade": "A",
          "confidence": 87.5,
          "currentPrice": 0.02,
          "entryZone": [
            0.01959,
            0.0201
          ],
          "stopLoss": 0.02164,
          "takeProfit": 0.015215,
          "riskReward": 2.9,
          "positionPct": 6,
          "kellyPct": 12.5,
          "invalidation": 0.02164,
          "sources": [
            {
              "name": "bigorder_anomaly",
              "score": 51
            },
            {
              "name": "quantitative",
              "score": 2
            },
            {
              "name": "technical",
              "score": 10
            }
          ],
          "winRate": null,
          "sampleCount": null,
          "avgProfit": null
        },
        "math": {
          "hurst": 0.5,
          "mcBullProb": 0.37,
          "volatility": "low",
          "marketRegime": "quiet"
        },
        "strategy": {
          "version": 1,
          "regime": "quiet",
          "globalWinRate": 0.5
        }
      }
    },
    {
      "type": "signalCard",
      "data": {
        "displayText": "📊 WLFI 交易信号卡 | 🟡A级 | 置信度 88%\n├─ 方向：做空\n├─ 当前价格：$0.0600\n├─ 进场区间：$0.0597 - $0.0603\n├─ 止损：$0.0615 (+2.4%)\n├─ 止盈：$0.0576 (-4.1%)\n├─ 盈亏比：1.7 : 1\n├─ 建议仓位：总资金 6%（经风险调整后的实际仓位）\n├─ Kelly 仓位：12.5%（理论最优仓位，建议仓位取其半值防回撤）\n├─ 依据：大单异动(57) + 量化六因子(19) + 技术分析(17)\n├─ 数学推导：Hurst=0.50 | MC 看跌77% | 波动率=low | 市场=trending_down | Kelly=12.5%\n│  · MC上涨概率仅23%，方向存疑\n│  · VaR(95%)=-36.4%，尾部风险大\n│  · 波动率低位(P8)，趋势可靠\n├─ 历史胜率：--（近30天 -- 次）\n├─ 平均盈利：--\n├─ 策略v1 | trending_down | 全局胜率50%\n└─ 失效条件：突破 $0.0615",
        "kellyPct": 12.5,
        "card": {
          "coin": "WLFI",
          "direction": "short",
          "grade": "A",
          "confidence": 87.5,
          "currentPrice": 0.06,
          "entryZone": [
            0.059706,
            0.060294
          ],
          "stopLoss": 0.061468,
          "takeProfit": 0.057554,
          "riskReward": 1.7,
          "positionPct": 6,
          "kellyPct": 12.5,
          "invalidation": 0.061468,
          "sources": [
            {
              "name": "bigorder_anomaly",
              "score": 57
            },
            {
              "name": "quantitative",
              "score": 19
            },
            {
              "name": "technical",
              "score": 17
            }
          ],
          "winRate": null,
          "sampleCount": null,
          "avgProfit": null
        },
        "math": {
          "hurst": 0.5,
          "mcBullProb": 0.234,
          "volatility": "low",
          "marketRegime": "trending_down"
        },
        "strategy": {
          "version": 1,
          "regime": "trending_down",
          "globalWinRate": 0.5
        }
      }
    },
    {
      "type": "signalCard",
      "data": {
        "displayText": "📊 WAL 交易信号卡 | 🟡A级 | 置信度 88%\n├─ 方向：做空\n├─ 当前价格：$0.0300\n├─ 进场区间：$0.0296 - $0.0301\n├─ 止损：$0.0329 (+9.7%)\n├─ 止盈：$0.0271 (-9.7%)\n├─ 盈亏比：1.0 : 1\n├─ 建议仓位：总资金 6%（经风险调整后的实际仓位）\n├─ Kelly 仓位：12.5%（理论最优仓位，建议仓位取其半值防回撤）\n├─ 依据：大单异动(15) + 量化六因子(19) + 技术分析(35)\n├─ 数学推导：Hurst=0.50 | MC 看跌84% | 波动率=normal | 市场=mean_reverting | Kelly=12.5%\n│  · 可预测性57%，信号可靠性高\n│  · MC上涨概率仅16%，方向存疑\n│  · VaR(95%)=-74.6%，尾部风险大\n├─ 历史胜率：--（近30天 -- 次）\n├─ 平均盈利：--\n├─ 策略v1 | mean_reverting | 全局胜率50%\n└─ 失效条件：突破 $0.0329",
        "kellyPct": 12.5,
        "card": {
          "coin": "WAL",
          "direction": "short",
          "grade": "A",
          "confidence": 87.5,
          "currentPrice": 0.03,
          "entryZone": [
            0.029562,
            0.03015
          ],
          "stopLoss": 0.032919,
          "takeProfit": 0.027081,
          "riskReward": 1.0,
          "positionPct": 6,
          "kellyPct": 12.5,
          "invalidation": 0.032919,
          "sources": [
            {
              "name": "bigorder_anomaly",
              "score": 15
            },
            {
              "name": "quantitative",
              "score": 19
            },
            {
              "name": "technical",
              "score": 35
            }
          ],
          "winRate": null,
          "sampleCount": null,
          "avgProfit": null
        },
        "math": {
          "hurst": 0.5,
          "mcBullProb": 0.163,
          "volatility": "normal",
          "marketRegime": "mean_reverting"
        },
        "strategy": {
          "version": 1,
          "regime": "mean_reverting",
          "globalWinRate": 0.5
        }
      }
    },
    {
      "type": "signalCard",
      "data": {
        "displayText": "📊 SUI 交易信号卡 | 🟡A级 | 置信度 84%\n├─ 方向：做空\n├─ 当前价格：$0.7500\n├─ 进场区间：$0.7465 - $0.7535\n├─ 止损：$0.7674 (+2.3%)\n├─ 止盈：$0.7210 (-3.9%)\n├─ 盈亏比：1.7 : 1\n├─ 建议仓位：总资金 6%（经风险调整后的实际仓位）\n├─ Kelly 仓位：12.5%（理论最优仓位，建议仓位取其半值防回撤）\n├─ 依据：大单异动(42) + 量化六因子(27) + 技术分析(55)\n├─ 数学推导：Hurst=0.50 | MC 看跌70% | 波动率=normal | 市场=trending_down | Kelly=12.5%\n│  · MC上涨概率仅30%，方向存疑\n│  · VaR(95%)=-39.0%，尾部风险大\n├─ 历史胜率：--（近30天 -- 次）\n├─ 平均盈利：--\n├─ 策略v1 | trending_down | 全局胜率50%\n└─ 失效条件：突破 $0.7674",
        "kellyPct": 12.5,
        "card": {
          "coin": "SUI",
          "direction": "short",
          "grade": "A",
          "confidence": 84.5,
          "currentPrice": 0.75,
          "entryZone": [
            0.746515,
            0.753485
          ],
          "stopLoss": 0.767425,
          "takeProfit": 0.720959,
          "riskReward": 1.7,
          "positionPct": 6,
          "kellyPct": 12.5,
          "invalidation": 0.767425,
          "sources": [
            {
              "name": "bigorder_anomaly",
              "score": 42
            },
            {
              "name": "quantitative",
              "score": 27
            },
            {
              "name": "technical",
              "score": 55
            }
          ],
          "winRate": null,
          "sampleCount": null,
          "avgProfit": null
        },
        "math": {
          "hurst": 0.5,
          "mcBullProb": 0.295,
          "volatility": "normal",
          "marketRegime": "trending_down"
        },
        "strategy": {
          "version": 1,
          "regime": "trending_down",
          "globalWinRate": 0.5
        }
      }
    },
    {
      "type": "signalCard",
      "data": {
        "displayText": "📊 DASH 交易信号卡 | 🟡A级 | 置信度 84%\n├─ 方向：做空\n├─ 当前价格：$34.62\n├─ 进场区间：$34.39 - $34.79\n├─ 止损：$35.77 (+3.3%)\n├─ 止盈：$32.70 (-5.5%)\n├─ 盈亏比：1.7 : 1\n├─ 建议仓位：总资金 6%（经风险调整后的实际仓位）\n├─ Kelly 仓位：12.5%（理论最优仓位，建议仓位取其半值防回撤）\n├─ 依据：大单异动(42) + 量化六因子(17) + 技术分析(35)\n├─ 数学推导：Hurst=0.50 | MC 看跌71% | 波动率=normal | 市场=trending_down | Kelly=12.5%\n│  · MC上涨概率仅29%，方向存疑\n│  · VaR(95%)=-49.6%，尾部风险大\n├─ 历史胜率：--（近30天 -- 次）\n├─ 平均盈利：--\n├─ 策略v1 | trending_down | 全局胜率50%\n└─ 失效条件：突破 $35.77",
        "kellyPct": 12.5,
        "card": {
          "coin": "DASH",
          "direction": "short",
          "grade": "A",
          "confidence": 84.5,
          "currentPrice": 34.62,
          "entryZone": [
            34.3898,
            34.7931
          ],
          "stopLoss": 35.771,
          "takeProfit": 32.7017,
          "riskReward": 1.7,
          "positionPct": 6,
          "kellyPct": 12.5,
          "invalidation": 35.771,
          "sources": [
            {
              "name": "bigorder_anomaly",
              "score": 42
            },
            {
              "name": "quantitative",
              "score": 17
            },
            {
              "name": "technical",
              "score": 35
            }
          ],
          "winRate": null,
          "sampleCount": null,
          "avgProfit": null
        },
        "math": {
          "hurst": 0.5,
          "mcBullProb": 0.29,
          "volatility": "normal",
          "marketRegime": "trending_down"
        },
        "strategy": {
          "version": 1,
          "regime": "trending_down",
          "globalWinRate": 0.5
        }
      }
    },
    {
      "type": "signalCard",
      "data": {
        "displayText": "📊 FIL 交易信号卡 | 🟡A级 | 置信度 84%\n├─ 方向：做空\n├─ 当前价格：$0.7600\n├─ 进场区间：$0.7562 - $0.7638\n├─ 止损：$0.7792 (+2.5%)\n├─ 止盈：$0.7280 (-4.2%)\n├─ 盈亏比：1.7 : 1\n├─ 建议仓位：总资金 6%（经风险调整后的实际仓位）\n├─ Kelly 仓位：12.5%（理论最优仓位，建议仓位取其半值防回撤）\n├─ 依据：大单异动(55) + 量化六因子(1) + 技术分析(30)\n├─ 数学推导：Hurst=0.50 | MC 看跌66% | 波动率=normal | 市场=trending_down | Kelly=12.5%\n│  · MC上涨概率仅34%，方向存疑\n│  · VaR(95%)=-40.0%，尾部风险大\n├─ 历史胜率：--（近30天 -- 次）\n├─ 平均盈利：--\n├─ 策略v1 | trending_down | 全局胜率50%\n└─ 失效条件：突破 $0.7792",
        "kellyPct": 12.5,
        "card": {
          "coin": "FIL",
          "direction": "short",
          "grade": "A",
          "confidence": 84.5,
          "currentPrice": 0.76,
          "entryZone": [
            0.756166,
            0.7638
          ],
          "stopLoss": 0.779172,
          "takeProfit": 0.728047,
          "riskReward": 1.7,
          "positionPct": 6,
          "kellyPct": 12.5,
          "invalidation": 0.779172,
          "sources": [
            {
              "name": "bigorder_anomaly",
              "score": 55
            },
            {
              "name": "quantitative",
              "score": 1
            },
            {
              "name": "technical",
              "score": 30
            }
          ],
          "winRate": null,
          "sampleCount": null,
          "avgProfit": null
        },
        "math": {
          "hurst": 0.5,
          "mcBullProb": 0.336,
          "volatility": "normal",
          "marketRegime": "trending_down"
        },
        "strategy": {
          "version": 1,
          "regime": "trending_down",
          "globalWinRate": 0.5
        }
      }
    },
    {
      "type": "signalCard",
      "data": {
        "displayText": "📊 ARB 交易信号卡 | 🟡A级 | 置信度 84%\n├─ 方向：做空\n├─ 当前价格：$0.0800\n├─ 进场区间：$0.0796 - $0.0804\n├─ 止损：$0.0818 (+2.3%)\n├─ 止盈：$0.0770 (-3.8%)\n├─ 盈亏比：1.7 : 1\n├─ 建议仓位：总资金 6%（经风险调整后的实际仓位）\n├─ Kelly 仓位：12.5%（理论最优仓位，建议仓位取其半值防回撤）\n├─ 依据：大单异动(55) + 量化六因子(11) + 技术分析(20)\n├─ 数学推导：Hurst=0.50 | MC 看跌84% | 波动率=normal | 市场=trending_down | Kelly=12.5%\n│  · MC上涨概率仅16%，方向存疑\n│  · VaR(95%)=-38.9%，尾部风险大\n├─ 历史胜率：--（近30天 -- 次）\n├─ 平均盈利：--\n├─ 策略v1 | trending_down | 全局胜率50%\n└─ 失效条件：突破 $0.0818",
        "kellyPct": 12.5,
        "card": {
          "coin": "ARB",
          "direction": "short",
          "grade": "A",
          "confidence": 84.5,
          "currentPrice": 0.08,
          "entryZone": [
            0.07964,
            0.08036
          ],
          "stopLoss": 0.081802,
          "takeProfit": 0.076997,
          "riskReward": 1.7,
          "positionPct": 6,
          "kellyPct": 12.5,
          "invalidation": 0.081802,
          "sources": [
            {
              "name": "bigorder_anomaly",
              "score": 55
            },
            {
              "name": "quantitative",
              "score": 11
            },
            {
              "name": "technical",
              "score": 20
            }
          ],
          "winRate": null,
          "sampleCount": null,
          "avgProfit": null
        },
        "math": {
          "hurst": 0.5,
          "mcBullProb": 0.157,
          "volatility": "normal",
          "marketRegime": "trending_down"
        },
        "strategy": {
          "version": 1,
          "regime": "trending_down",
          "globalWinRate": 0.5
        }
      }
    },
    {
      "type": "signalCard",
      "data": {
        "displayText": "📊 ICP 交易信号卡 | 🟡A级 | 置信度 84%\n├─ 方向：做空\n├─ 当前价格：$2.27\n├─ 进场区间：$2.26 - $2.28\n├─ 止损：$2.32 (+2.4%)\n├─ 止盈：$2.18 (-4.0%)\n├─ 盈亏比：1.7 : 1\n├─ 建议仓位：总资金 6%（经风险调整后的实际仓位）\n├─ Kelly 仓位：12.5%（理论最优仓位，建议仓位取其半值防回撤）\n├─ 依据：大单异动(50) + 量化六因子(10) + 技术分析(15)\n├─ 数学推导：Hurst=0.50 | MC 看跌61% | 波动率=normal | 市场=trending_down | Kelly=12.5%\n│  · MC上涨概率仅39%，方向存疑\n│  · VaR(95%)=-43.4%，尾部风险大\n├─ 历史胜率：--（近30天 -- 次）\n├─ 平均盈利：--\n├─ 策略v1 | trending_down | 全局胜率50%\n└─ 失效条件：突破 $2.32",
        "kellyPct": 12.5,
        "card": {
          "coin": "ICP",
          "direction": "short",
          "grade": "A",
          "confidence": 84.5,
          "currentPrice": 2.27,
          "entryZone": [
            2.2591,
            2.2809
          ],
          "stopLoss": 2.3245,
          "takeProfit": 2.1791,
          "riskReward": 1.7,
          "positionPct": 6,
          "kellyPct": 12.5,
          "invalidation": 2.3245,
          "sources": [
            {
              "name": "bigorder_anomaly",
              "score": 50
            },
            {
              "name": "quantitative",
              "score": 10
            },
            {
              "name": "technical",
              "score": 15
            }
          ],
          "winRate": null,
          "sampleCount": null,
          "avgProfit": null
        },
        "math": {
          "hurst": 0.5,
          "mcBullProb": 0.388,
          "volatility": "normal",
          "marketRegime": "trending_down"
        },
        "strategy": {
          "version": 1,
          "regime": "trending_down",
          "globalWinRate": 0.5
        }
      }
    },
    {
      "type": "signalCard",
      "data": {
        "displayText": "📊 DOGE 交易信号卡 | 🟡A级 | 置信度 80%\n├─ 方向：做空\n├─ 当前价格：$0.0800\n├─ 进场区间：$0.0796 - $0.0804\n├─ 止损：$0.0818 (+2.2%)\n├─ 止盈：$0.0770 (-3.7%)\n├─ 盈亏比：1.7 : 1\n├─ 建议仓位：总资金 6%（经风险调整后的实际仓位）\n├─ Kelly 仓位：12.5%（理论最优仓位，建议仓位取其半值防回撤）\n├─ 依据：大单异动(62) + 量化六因子(8) + 技术分析(20)\n├─ 数学推导：Hurst=0.50 | MC 看跌70% | 波动率=normal | 市场=trending_down | Kelly=12.5%\n│  · 可预测性24%过低，噪音主导\n│  · MC上涨概率仅30%，方向存疑\n│  · VaR(95%)=-27.0%，尾部风险大\n├─ 历史胜率：--（近30天 -- 次）\n├─ 平均盈利：--\n├─ 策略v1 | trending_down | 全局胜率50%\n└─ 失效条件：突破 $0.0818",
        "kellyPct": 12.5,
        "card": {
          "coin": "DOGE",
          "direction": "short",
          "grade": "A",
          "confidence": 80.0,
          "currentPrice": 0.08,
          "entryZone": [
            0.07964,
            0.08036
          ],
          "stopLoss": 0.0818,
          "takeProfit": 0.077,
          "riskReward": 1.7,
          "positionPct": 6,
          "kellyPct": 12.5,
          "invalidation": 0.0818,
          "sources": [
            {
              "name": "bigorder_anomaly",
              "score": 62
            },
            {
              "name": "quantitative",
              "score": 8
            },
            {
              "name": "technical",
              "score": 20
            }
          ],
          "winRate": null,
          "sampleCount": null,
          "avgProfit": null
        },
        "math": {
          "hurst": 0.5,
          "mcBullProb": 0.301,
          "volatility": "normal",
          "marketRegime": "trending_down"
        },
        "strategy": {
          "version": 1,
          "regime": "trending_down",
          "globalWinRate": 0.5
        }
      }
    },
    {
      "type": "signalCard",
      "data": {
        "displayText": "📊 XRP 交易信号卡 | 🟡A级 | 置信度 80%\n├─ 方向：做空\n├─ 当前价格：$1.12\n├─ 进场区间：$1.11 - $1.12\n├─ 止损：$1.15 (+2.2%)\n├─ 止盈：$1.08 (-3.7%)\n├─ 盈亏比：1.7 : 1\n├─ 建议仓位：总资金 6%（经风险调整后的实际仓位）\n├─ Kelly 仓位：12.5%（理论最优仓位，建议仓位取其半值防回撤）\n├─ 依据：大单异动(51) + 量化六因子(16) + 技术分析(45)\n├─ 数学推导：Hurst=0.50 | MC 看跌78% | 波动率=normal | 市场=trending_down | Kelly=12.5%\n│  · 可预测性13%过低，噪音主导\n│  · MC上涨概率仅22%，方向存疑\n│  · VaR(95%)=-23.6%，尾部风险大\n├─ 历史胜率：--（近30天 -- 次）\n├─ 平均盈利：--\n├─ 策略v1 | trending_down | 全局胜率50%\n└─ 失效条件：突破 $1.15",
        "kellyPct": 12.5,
        "card": {
          "coin": "XRP",
          "direction": "short",
          "grade": "A",
          "confidence": 80.0,
          "currentPrice": 1.12,
          "entryZone": [
            1.115,
            1.125
          ],
          "stopLoss": 1.1452,
          "takeProfit": 1.078,
          "riskReward": 1.7,
          "positionPct": 6,
          "kellyPct": 12.5,
          "invalidation": 1.1452,
          "sources": [
            {
              "name": "bigorder_anomaly",
              "score": 51
            },
            {
              "name": "quantitative",
              "score": 16
            },
            {
              "name": "technical",
              "score": 45
            }
          ],
          "winRate": null,
          "sampleCount": null,
          "avgProfit": null
        },
        "math": {
          "hurst": 0.5,
          "mcBullProb": 0.217,
          "volatility": "normal",
          "marketRegime": "trending_down"
        },
        "strategy": {
          "version": 1,
          "regime": "trending_down",
          "globalWinRate": 0.5
        }
      }
    },
    {
      "type": "signalCard",
      "data": {
        "displayText": "📊 PEPE 交易信号卡 | 🟡A级 | 置信度 80%\n├─ 方向：做空\n├─ 当前价格：$0.00000285\n├─ 进场区间：$0.000002836892 - $0.000002863108\n├─ 止损：$0.00000291554 (+2.3%)\n├─ 止盈：$0.000002740767 (-3.8%)\n├─ 盈亏比：1.7 : 1\n├─ 建议仓位：总资金 6%（经风险调整后的实际仓位）\n├─ Kelly 仓位：12.5%（理论最优仓位，建议仓位取其半值防回撤）\n├─ 依据：大单异动(56) + 量化六因子(14) + 技术分析(25)\n├─ 数学推导：Hurst=0.50 | MC 看跌82% | 波动率=normal | 市场=trending_down | Kelly=12.5%\n│  · 可预测性11%过低，噪音主导\n│  · MC上涨概率仅18%，方向存疑\n│  · VaR(95%)=-30.6%，尾部风险大\n├─ 历史胜率：--（近30天 -- 次）\n├─ 平均盈利：--\n├─ 策略v1 | trending_down | 全局胜率50%\n└─ 失效条件：突破 $0.00000291554",
        "kellyPct": 12.5,
        "card": {
          "coin": "PEPE",
          "direction": "short",
          "grade": "A",
          "confidence": 80.0,
          "currentPrice": 2.85e-06,
          "entryZone": [
            2.836892e-06,
            2.863108e-06
          ],
          "stopLoss": 2.91554e-06,
          "takeProfit": 2.740767e-06,
          "riskReward": 1.7,
          "positionPct": 6,
          "kellyPct": 12.5,
          "invalidation": 2.91554e-06,
          "sources": [
            {
              "name": "bigorder_anomaly",
              "score": 56
            },
            {
              "name": "quantitative",
              "score": 14
            },
            {
              "name": "technical",
              "score": 25
            }
          ],
          "winRate": null,
          "sampleCount": null,
          "avgProfit": null
        },
        "math": {
          "hurst": 0.5,
          "mcBullProb": 0.18,
          "volatility": "normal",
          "marketRegime": "trending_down"
        },
        "strategy": {
          "version": 1,
          "regime": "trending_down",
          "globalWinRate": 0.5
        }
      }
    },
    {
      "type": "signalCard",
      "data": {
        "displayText": "📊 ENA 交易信号卡 | 🟡A级 | 置信度 74%\n├─ 方向：做空\n├─ 当前价格：$0.0800\n├─ 进场区间：$0.0794 - $0.0804\n├─ 止损：$0.0828 (+3.5%)\n├─ 止盈：$0.0754 (-5.8%)\n├─ 盈亏比：1.7 : 1\n├─ 建议仓位：总资金 6%（经风险调整后的实际仓位）\n├─ Kelly 仓位：12.5%（理论最优仓位，建议仓位取其半值防回撤）\n├─ 依据：大单异动(46) + 量化六因子(11) + 技术分析(25)\n├─ 数学推导：Hurst=0.50 | MC 看跌66% | 波动率=extreme | 市场=trending_down | Kelly=12.5%\n│  · 可预测性23%过低，噪音主导\n│  · MC上涨概率仅34%，方向存疑\n│  · VaR(95%)=-44.2%，尾部风险大\n├─ 历史胜率：--（近30天 -- 次）\n├─ 平均盈利：--\n├─ 策略v1 | trending_down | 全局胜率50%\n└─ 失效条件：突破 $0.0828",
        "kellyPct": 12.5,
        "card": {
          "coin": "ENA",
          "direction": "short",
          "grade": "A",
          "confidence": 74.0,
          "currentPrice": 0.08,
          "entryZone": [
            0.079443,
            0.0804
          ],
          "stopLoss": 0.082784,
          "takeProfit": 0.07536,
          "riskReward": 1.7,
          "positionPct": 6,
          "kellyPct": 12.5,
          "invalidation": 0.082784,
          "sources": [
            {
              "name": "bigorder_anomaly",
              "score": 46
            },
            {
              "name": "quantitative",
              "score": 11
            },
            {
              "name": "technical",
              "score": 25
            }
          ],
          "winRate": null,
          "sampleCount": null,
          "avgProfit": null
        },
        "math": {
          "hurst": 0.5,
          "mcBullProb": 0.339,
          "volatility": "extreme",
          "marketRegime": "trending_down"
        },
        "strategy": {
          "version": 1,
          "regime": "trending_down",
          "globalWinRate": 0.5
        }
      }
    },
    {
      "type": "signalCard",
      "data": {
        "displayText": "📊 PUMP 交易信号卡 | 🟡A级 | 置信度 74%\n├─ 方向：做空\n├─ 当前价格：$0.001628\n├─ 进场区间：$0.00162 - $0.001636\n├─ 止损：$0.001669 (+2.5%)\n├─ 止盈：$0.00156 (-4.2%)\n├─ 盈亏比：1.7 : 1\n├─ 建议仓位：总资金 6%（经风险调整后的实际仓位）\n├─ Kelly 仓位：12.5%（理论最优仓位，建议仓位取其半值防回撤）\n├─ 依据：大单异动(19) + 量化六因子(18) + 技术分析(40)\n├─ 数学推导：Hurst=0.50 | MC 看跌68% | 波动率=extreme | 市场=trending_down | Kelly=12.5%\n│  · 可预测性17%过低，噪音主导\n│  · MC上涨概率仅32%，方向存疑\n│  · VaR(95%)=-34.7%，尾部风险大\n├─ 历史胜率：--（近30天 -- 次）\n├─ 平均盈利：--\n├─ 策略v1 | trending_down | 全局胜率50%\n└─ 失效条件：突破 $0.001669",
        "kellyPct": 12.5,
        "card": {
          "coin": "PUMP",
          "direction": "short",
          "grade": "A",
          "confidence": 74.0,
          "currentPrice": 0.001628,
          "entryZone": [
            0.00162,
            0.001636
          ],
          "stopLoss": 0.001669,
          "takeProfit": 0.00156,
          "riskReward": 1.7,
          "positionPct": 6,
          "kellyPct": 12.5,
          "invalidation": 0.001669,
          "sources": [
            {
              "name": "bigorder_anomaly",
              "score": 19
            },
            {
              "name": "quantitative",
              "score": 18
            },
            {
              "name": "technical",
              "score": 40
            }
          ],
          "winRate": null,
          "sampleCount": null,
          "avgProfit": null
        },
        "math": {
          "hurst": 0.5,
          "mcBullProb": 0.322,
          "volatility": "extreme",
          "marketRegime": "trending_down"
        },
        "strategy": {
          "version": 1,
          "regime": "trending_down",
          "globalWinRate": 0.5
        }
      }
    },
    {
      "type": "signalCard",
      "data": {
        "displayText": "📊 SEI 交易信号卡 | 🟡A级 | 置信度 74%\n├─ 方向：做空\n├─ 当前价格：$0.0500\n├─ 进场区间：$0.0497 - $0.0503\n├─ 止损：$0.0514 (+2.8%)\n├─ 止盈：$0.0477 (-4.6%)\n├─ 盈亏比：1.7 : 1\n├─ 建议仓位：总资金 6%（经风险调整后的实际仓位）\n├─ Kelly 仓位：12.5%（理论最优仓位，建议仓位取其半值防回撤）\n├─ 依据：大单异动(42) + 量化六因子(11) + 技术分析(10)\n├─ 数学推导：Hurst=0.50 | MC 看跌62% | 波动率=extreme | 市场=trending_down | Kelly=12.5%\n│  · 可预测性17%过低，噪音主导\n│  · MC上涨概率仅38%，方向存疑\n│  · VaR(95%)=-35.6%，尾部风险大\n├─ 历史胜率：--（近30天 -- 次）\n├─ 平均盈利：--\n├─ 策略v1 | trending_down | 全局胜率50%\n└─ 失效条件：突破 $0.0514",
        "kellyPct": 12.5,
        "card": {
          "coin": "SEI",
          "direction": "short",
          "grade": "A",
          "confidence": 74.0,
          "currentPrice": 0.05,
          "entryZone": [
            0.049723,
            0.05025
          ],
          "stopLoss": 0.051386,
          "takeProfit": 0.047691,
          "riskReward": 1.7,
          "positionPct": 6,
          "kellyPct": 12.5,
          "invalidation": 0.051386,
          "sources": [
            {
              "name": "bigorder_anomaly",
              "score": 42
            },
            {
              "name": "quantitative",
              "score": 11
            },
            {
              "name": "technical",
              "score": 10
            }
          ],
          "winRate": null,
          "sampleCount": null,
          "avgProfit": null
        },
        "math": {
          "hurst": 0.5,
          "mcBullProb": 0.379,
          "volatility": "extreme",
          "marketRegime": "trending_down"
        },
        "strategy": {
          "version": 1,
          "regime": "trending_down",
          "globalWinRate": 0.5
        }
      }
    }
  ],
  "cached_at": "2026-06-10 15:22:53"
}